fore/__init__.py
fore/foresight/__init__.py
fore/foresight/client.py
fore/foresight/client_test.py
fore/foresight/schema.py
fore/foresight/utils.py
fore-0.1.8.dist-info/LICENSE
fore-0.1.8.dist-info/METADATA
fore-0.1.8.dist-info/WHEEL
fore-0.1.8.dist-info/top_level.txt
fore-0.1.8.dist-info/RECORD
