Metadata-Version: 2.1
Name: fore
Version: 0.1.8
Summary: fore ai packages
Author-email: fore ai <info@foreai.co>
Maintainer-email: fore ai <info@foreai.co>
License: Apache 2.0 License
Project-URL: Homepage, https://foreai.co
Project-URL: Repository, https://github.com/foreai-co/fore
Project-URL: Issues, https://github.com/foreai-co/fore/issues
Requires-Python: >=3.8
License-File: LICENSE
Requires-Dist: pydantic>2.5
Requires-Dist: requests
Provides-Extra: extras
Requires-Dist: pandas; extra == "extras"
Provides-Extra: all
Requires-Dist: fore[extras]; extra == "all"
